tmtool/__init__.py
tmtool/tools.py
tmtool/util.py
yxytmtoolP-0.0.4.dist-info/METADATA
yxytmtoolP-0.0.4.dist-info/WHEEL
yxytmtoolP-0.0.4.dist-info/top_level.txt
yxytmtoolP-0.0.4.dist-info/RECORD
