Metadata-Version: 2.1
Name: yxytmtoolP
Version: 0.0.4
Summary: tmtool
Home-page: UNKNOWN
Author: yangxinying
Author-email: 
License: MIT
Platform: UNKNOWN
Classifier: License :: OSI Approved :: MIT License
Classifier: Programming Language :: Python
Classifier: Programming Language :: Python :: 3
Requires-Python: >=3.8.5
Requires-Dist: yagmail
Requires-Dist: json
